adqol/persist/__init__.py
adqol/persist/decoratorutil.py
adqol/persist/dydb.py
adqol/persist/entity.py
adqol/persist/fielduse.py
adqol_persist-0.0.4.dist-info/LICENSE.txt
adqol_persist-0.0.4.dist-info/METADATA
adqol_persist-0.0.4.dist-info/WHEEL
adqol_persist-0.0.4.dist-info/top_level.txt
adqol_persist-0.0.4.dist-info/RECORD
