Metadata-Version: 2.1
Name: adqol-persist
Version: 0.0.4
Summary: Dynamo DB Persistence Framework
Home-page: https://github.com/jhmjesus/adqol-persist
Author: Jose Horacio Mello de Jesus
Author-email: jhmjesus@gmail.com
License: UNKNOWN
Keywords: DynamoDB,Analise Descritiva Qualitativa,Descriptive Qualitative Analyze
Platform: UNKNOWN
Classifier: Programming Language :: Python :: 3
Classifier: License :: OSI Approved :: MIT License
Classifier: Operating System :: OS Independent
Requires-Python: >=3.6
Requires-Dist: boto3 (==1.20.48)
Requires-Dist: python-dotenv (==0.12.0)
